MANIFEST.in
README.rst
setup.py
gspreaddict/__init__.py
python_gspreaddict.egg-info/PKG-INFO
python_gspreaddict.egg-info/SOURCES.txt
python_gspreaddict.egg-info/dependency_links.txt
python_gspreaddict.egg-info/requires.txt
python_gspreaddict.egg-info/top_level.txt