Metadata-Version: 1.0
Name: python-gspreaddict
Version: 0.1.3
Summary: Google spread sheet as dictionary list. read-only.
Home-page: https://github.com/ytyng/python-gspreaddict.git
Author: ytyng
Author-email: ytyng@live.jp
License: MIT
Keywords: Google spreadsheet,python
Platform: UNKNOWN
